Workbook

Sheet Business_Data
A1: Date | B1: Region | C1: Product_Category | D1: Customer_Segment | E1: Units_Sold | F1: Revenue | G1: Cost | H1: Profit | I1: Profit Margin | J1: Revenue_per_Unit
A2: 45551 | B2: North | C2: Electronics | D2: Small Business | E2: 13 | F2: 56212 | G2: 30537.15 | H2: =Business_Data!$F2-Business_Data!$G2 -> 25674.85 | I2: =Business_Data!$H2/Business_Data!$F2 -> 0.45675034 | J2: =Business_Data!$F2/Business_Data!$E2 -> 4324
A3: 45577 | B3: East | C3: Accessories | D3: Corporate | E3: 96 | F3: 58176 | G3: 32401.66 | H3: =Business_Data!$F3-Business_Data!$G3 -> 25774.34 | I3: =Business_Data!$H3/Business_Data!$F3 -> 0.44304077 | J3: =Business_Data!$F3/Business_Data!$E3 -> 606
A4: 45532 | B4: West | C4: Electronics | D4: Corporate | E4: 135 | F4: 495720 | G4: 293744.19 | H4: =Business_Data!$F4-Business_Data!$G4 -> 201975.81 | I4: =Business_Data!$H4/Business_Data!$F4 -> 0.4074393 | J4: =Business_Data!$F4/Business_Data!$E4 -> 3672
A5: 45397 | B5: South | C5: Furniture | D5: Small Business | E5: 17 | F5: 43265 | G5: 31823.76 | H5: =Business_Data!$F5-Business_Data!$G5 -> 11441.24 | I5: =Business_Data!$H5/Business_Data!$F5 -> 0.26444563 | J5: =Business_Data!$F5/Business_Data!$E5 -> 2545
A6: 45441 | B6: North | C6: Furniture | D6: Consumer | E6: 170 | F6: 722670 | G6: 512630.04 | H6: =Business_Data!$F6-Business_Data!$G6 -> 210039.96 | I6: =Business_Data!$H6/Business_Data!$F6 -> 0.29064436 | J6: =Business_Data!$F6/Business_Data!$E6 -> 4251
A7: 45323 | B7: West | C7: Electronics | D7: Corporate | E7: 165 | F7: 760980 | G7: 576624.17 | H7: =Business_Data!$F7-Business_Data!$G7 -> 184355.83 | I7: =Business_Data!$H7/Business_Data!$F7 -> 0.24226107 | J7: =Business_Data!$F7/Business_Data!$E7 -> 4612
A8: 45561 | B8: East | C8: Furniture | D8: Corporate | E8: 191 | F8: 788639 | G8: 666249.47 | H8: =Business_Data!$F8-Business_Data!$G8 -> 122389.53 | I8: =Business_Data!$H8/Business_Data!$F8 -> 0.15519082 | J8: =Business_Data!$F8/Business_Data!$E8 -> 4129
A9: 45301 | B9: East | C9: Electronics | D9: Small Business | E9: 74 | F9: 211862 | G9: 125269.56 | H9: =Business_Data!$F9-Business_Data!$G9 -> 86592.44 | I9: =Business_Data!$H9/Business_Data!$F9 -> 0.40872096 | J9: =Business_Data!$F9/Business_Data!$E9 -> 2863
A10: 45591 | B10: West | C10: Electronics | D10: Consumer | E10: 46 | F10: 216522 | G10: 140557.47 | H10: =Business_Data!$F10-Business_Data!$G10 -> 75964.53 | I10: =Business_Data!$H10/Business_Data!$F10 -> 0.35083978 | J10: =Business_Data!$F10/Business_Data!$E10 -> 4707
A11: 45333 | B11: South | C11: Electronics | D11: Consumer | E11: 157 | F11: 647468 | G11: 386079.85 | H11: =Business_Data!$F11-Business_Data!$G11 -> 261388.15 | I11: =Business_Data!$H11/Business_Data!$F11 -> 0.40370821 | J11: =Business_Data!$F11/Business_Data!$E11 -> 4124
A12: 45321 | B12: East | C12: Furniture | D12: Corporate | E12: 69 | F12: 87837 | G12: 70487.1 | H12: =Business_Data!$F12-Business_Data!$G12 -> 17349.9 | I12: =Business_Data!$H12/Business_Data!$F12 -> 0.19752382 | J12: =Business_Data!$F12/Business_Data!$E12 -> 1273
A13: 45575 | B13: North | C13: Accessories | D13: Corporate | E13: 118 | F13: 122720 | G13: 66758.11 | H13: =Business_Data!$F13-Business_Data!$G13 -> 55961.89 | I13: =Business_Data!$H13/Business_Data!$F13 -> 0.45601279 | J13: =Business_Data!$F13/Business_Data!$E13 -> 1040
... A201: 45616 | B201: East | C201: Accessories | D201: Small Business | E201: 119 | F201: 501228 | G201: 369495.33 | H201: =Business_Data!$F201-Business_Data!$G201 -> 131732.67 | I201: =Business_Data!$H201/Business_Data!$F201 -> 0.26281985 | J201: =Business_Data!$F201/Business_Data!$E201 -> 4212

Sheet Region Analysis
F1: Revenue by Region
A3: Row Labels | B3: Sum of Units_Sold | C3: Sum of Revenue | D3: Sum of Profit
A4: East | B4: 4529 | C4: 13645621 | D4: 3983183.2
A5: North | B5: 5305 | C5: 14553584 | D5: 4891279.1
A6: South | B6: 4965 | C6: 15183789 | D6: 5309366.8
A7: West | B7: 5023 | C7: 13648326 | D7: 4270128.4
A8: Grand Total | B8: 19822 | C8: 57031320 | D8: 18453958
B11: INSIGHTS
B12: South has the highest revenue (~15.18M)

Sheet Product Category Analysis
B1: Revenue Contribution by Product Category
A3: Row Labels | B3: Sum of Units_Sold | C3: Sum of Profit | D3: Sum of Revenue
A4: Accessories | B4: 6506 | C4: 6260650.2 | D4: 19134558
A5: Electronics | B5: 6977 | C5: 6851416.2 | D5: 21596324
A6: Furniture | B6: 6339 | C6: 5341891.1 | D6: 16300438
A7: Grand Total | B7: 19822 | C7: 18453958 | D7: 57031320
C11: INSIGHTS
B12: Electronics is the top performing category

Sheet Customer Segment Analysis
E1: Revenue by Customer Segment
A3: Row Labels | B3: Sum of Revenue | C3: Sum of Profit
A4: Consumer | B4: 16576110 | C4: 5821989.5
A5: Corporate | B5: 21259177 | C5: 6697201.6
A6: Small Business | B6: 19196033 | C6: 5934766.5
A7: Grand Total | B7: 57031320 | C7: 18453958
B12: INSIGHTS
A13: Corporate customers generate the highest revenue

Sheet Monthly Revenue Trend
E2: Monthly Revenue Trend
A3: Row Labels | B3: Sum of Revenue | M3: Key observations:
A4: Jan | B4: 5702801
A5: Feb | B5: 5823253 | M5: Lowest month → September (~2.3M)
A6: Mar | B6: 2712858
A7: Apr | B7: 4769531 | M7: Highest months → October & November (~6.6M)
A8: May | B8: 5889054
A9: Jun | B9: 4085992
A10: Jul | B10: 3385036 | M10: INSIGHTS :
A11: Aug | B11: 4278154 | M11: Revenue spikes in Q4 (Oct–Nov)
A12: Sep | B12: 2328754
A13: Oct | B13: 6660146
A14: Nov | B14: 6689451
A15: Dec | B15: 4706290
A16: Grand Total | B16: 57031320 | P16: Q4: 4th quarter of the year

Sheet Key Insights
C5: Column1 | D5: Column2 | E5: Column3 | F5: Column4 | G5: Column5 | H5: Column6 | I5: Column7 | J5: Column8 | K5: Column9 | L5: Column10 | M5: Column11 | N5: Column12 | O5: Column13 | P5: Column14
D6: Key Business Insights
D8: 1. Regional Performance
D9: South region generated the highest revenue (~15.18M) and profit among all regions, indicating strong market demand.
D11: 2. Product Category Performance
D12: Electronics is the top-performing category with approximately 21.6M revenue, followed by Accessories and Furniture.
D14: 3. Customer Segment Contribution
D15: Corporate customers contribute the highest share of revenue (~21.25M), making them the most valuable customer segment.
D17: 4. Monthly Revenue Trend
D18: Revenue shows strong seasonality, with October and November recording the highest sales, while September has the lowest revenue.
D20: 5. Profitability Observation
D21: Electronics also generates the highest profit, suggesting strong margins and demand in this category.
